pyjams/__init__.py
pyjams/_version.py
pyjams/air_humidity.py
pyjams/alpha_equ_h2o.py
pyjams/alpha_kin_h2o.py
pyjams/argsort.py
pyjams/class_datetime.py
pyjams/closest.py
pyjams/date2date.py
pyjams/division.py
pyjams/fgui.py
pyjams/fsread.py
pyjams/gridcellarea.py
pyjams/helper.py
pyjams/kernel_regression.py
pyjams/mad.py
pyjams/mcplot.py
pyjams/means.py
pyjams/morris_method.py
pyjams/ncinfo.py
pyjams/ncread.py
pyjams/npyio.py
pyjams/pack.py
pyjams/position.py
pyjams/romanliterals.py
pyjams/sce.py
pyjams/screening.py
pyjams/str2tex.py
pyjams/tee.py
pyjams/text2plot.py
pyjams/color/__init__.py
pyjams/color/brewer_palettes.py
pyjams/color/color.py
pyjams/color/ipcc_palettes.py
pyjams/color/mathematica_palettes.py
pyjams/color/ncl_palettes.py
pyjams/color/oregon_palettes.py
pyjams/color/pyjams_palettes.py
pyjams/color/sron2012_palettes.py
pyjams/color/sron_palettes.py
pyjams/color/ufz_palettes.py
pyjams/const/__init__.py
pyjams/const/const.py
pyjams/functions/__init__.py
pyjams/functions/fit_functions.py
pyjams/functions/general_functions.py
pyjams/functions/logistic_function.py
pyjams/functions/opti_test_functions.py
pyjams/functions/sa_test_functions.py
pyjams/jams/__init__.py
pyjams/jams/apply_undef.py
pyjams/jams/area_poly.py
pyjams/jams/around.py
pyjams/jams/autostring.py
pyjams/jams/baseflow.py
pyjams/jams/brewer.py
pyjams/jams/climate_index_knoben.py
pyjams/jams/clockplot.py
pyjams/jams/convex_hull.py
pyjams/jams/correlate.py
pyjams/jams/cuntz_gleixner.py
pyjams/jams/dag.py
pyjams/jams/date2dec.py
pyjams/jams/dec2date.py
pyjams/jams/delta_isogsm2.py
pyjams/jams/dewpoint.py
pyjams/jams/dfgui.py
pyjams/jams/dielectric_water.py
pyjams/jams/eddysuite.py
pyjams/jams/ellipse_area.py
pyjams/jams/errormeasures.py
pyjams/jams/fftngo.py
pyjams/jams/fill_nonfinite.py
pyjams/jams/find_in_path.py
pyjams/jams/fwrite.py
pyjams/jams/gap2lai.py
pyjams/jams/get_angle.py
pyjams/jams/get_era5.py
pyjams/jams/get_isogsm2.py
pyjams/jams/get_nearest.py
pyjams/jams/grid_mid2edge.py
pyjams-2.3.dist-info/AUTHORS.rst
pyjams-2.3.dist-info/LICENSE
pyjams-2.3.dist-info/METADATA
pyjams-2.3.dist-info/WHEEL
pyjams-2.3.dist-info/entry_points.txt
pyjams-2.3.dist-info/top_level.txt
pyjams-2.3.dist-info/RECORD
