Metadata-Version: 2.1
Name: pyjams
Version: 2.3
Summary: pyjams: a general Python package with a wide variety of miscellaneous utility functions.
Home-page: https://github.com/mcuntz/pyjams
Author: Matthias Cuntz, Juliane Mai, Stephan Thober, Arndt Piayda
Author-email: mc@macu.de
Maintainer: Matthias Cuntz
Maintainer-email: mc@macu.de
License: MIT
Project-URL: Documentation, https://mcuntz.github.io/pyjams/
Project-URL: Source, https://github.com/mcuntz/pyjams
Project-URL: Tracker, https://github.com/mcuntz/pyjams/issues
Project-URL: Changelog, https://github.com/mcuntz/pyjams/blob/main/CHANGELOG.rst
Project-URL: Conda-Forge, https://anaconda.org/conda-forge/pyjams
Platform: any
Classifier: Development Status :: 5 - Production/Stable
Classifier: Intended Audience :: Developers
Classifier: Intended Audience :: End Users/Desktop
Classifier: Intended Audience :: Science/Research
Classifier: License :: OSI Approved :: MIT License
Classifier: Natural Language :: English
Classifier: Operating System :: MacOS
Classifier: Operating System :: MacOS :: MacOS X
Classifier: Operating System :: Microsoft
Classifier: Operating System :: Microsoft :: Windows
Classifier: Operating System :: POSIX
Classifier: Operating System :: Unix
Classifier: Programming Language :: Python
Classifier: Programming Language :: Python :: 3
Classifier: Programming Language :: Python :: 3 :: Only
Classifier: Programming Language :: Python :: 3.8
Classifier: Programming Language :: Python :: 3.9
Classifier: Programming Language :: Python :: 3.10
Classifier: Programming Language :: Python :: 3.11
Classifier: Programming Language :: Python :: 3.12
Classifier: Topic :: Scientific/Engineering
Classifier: Topic :: Scientific/Engineering :: Atmospheric Science
Classifier: Topic :: Scientific/Engineering :: Hydrology
Classifier: Topic :: Scientific/Engineering :: Mathematics
Classifier: Topic :: Software Development
Classifier: Topic :: Utilities
Requires-Python: >=3.8
License-File: LICENSE
License-File: AUTHORS.rst
Requires-Dist: numpy
Requires-Dist: scipy
Requires-Dist: matplotlib
Requires-Dist: pandas
Requires-Dist: cftime
Requires-Dist: netcdf4
Requires-Dist: schwimmbad
Requires-Dist: xlrd
Requires-Dist: openpyxl
Provides-Extra: doc
Requires-Dist: numpydoc>=1.1; extra == "doc"
Requires-Dist: jinja2>=2; extra == "doc"
Requires-Dist: sphinx>=3; extra == "doc"
Requires-Dist: sphinx-book-theme>=1.0.1; extra == "doc"
Provides-Extra: test
Requires-Dist: setuptools>=42; extra == "test"
Requires-Dist: coverage[toml]>=5.2.1; extra == "test"
Requires-Dist: pytest>=6.0; extra == "test"
Requires-Dist: pytest-cov>=2.11.0; extra == "test"
